nfttools/__init__.py
nfttools-0.1.2.dist-info/LICENSE
nfttools-0.1.2.dist-info/METADATA
nfttools-0.1.2.dist-info/WHEEL
nfttools-0.1.2.dist-info/top_level.txt
nfttools-0.1.2.dist-info/RECORD
