Metadata-Version: 2.1
Name: nfttools
Version: 0.1.2
Summary: help interacting with nftables
Home-page: https://www.github.com/towalink/nfttools
Author: Dirk Henrici
Author-email: towalink.nfttools@henrici.name
Project-URL: Repository, https://www.github.com/towalink/nfttools
Project-URL: PyPi, https://pypi.org/project/nfttools/
Keywords: nftables validation parsing
Classifier: Programming Language :: Python
Classifier: License :: OSI Approved :: MIT License
Classifier: Operating System :: POSIX :: Linux
Classifier: Development Status :: 3 - Alpha
Classifier: Intended Audience :: System Administrators
Classifier: Intended Audience :: Developers
Classifier: Intended Audience :: Information Technology
Requires-Python: >=3.7
License-File: LICENSE
Provides-Extra: nftables
Requires-Dist: pip-nftables ; extra == 'nftables'
Requires-Dist: jsonschema ; extra == 'nftables'
